fairyfly_grasshopper/__init__.py
fairyfly_grasshopper/src/FF Boundary.py
fairyfly_grasshopper/src/FF Cavity Material.py
fairyfly_grasshopper/src/FF Color Boundary Attributes.py
fairyfly_grasshopper/src/FF Color Shape Attributes.py
fairyfly_grasshopper/src/FF Deconstruct Material.py
fairyfly_grasshopper/src/FF Dump Objects.py
fairyfly_grasshopper/src/FF Load Objects.py
fairyfly_grasshopper/src/FF Meshing Control.py
fairyfly_grasshopper/src/FF Model to THMZ.py
fairyfly_grasshopper/src/FF Model.py
fairyfly_grasshopper/src/FF Radiant Environment.py
fairyfly_grasshopper/src/FF Read THERM Result.py
fairyfly_grasshopper/src/FF Read UFactor Result.py
fairyfly_grasshopper/src/FF Search Materials.py
fairyfly_grasshopper/src/FF Shape.py
fairyfly_grasshopper/src/FF Solid Material.py
fairyfly_grasshopper/src/FF Visualize Problem Areas.py
fairyfly_grasshopper/src/__init__.py
fairyfly_grasshopper/user_objects/FF Boundary Attributes.ghuser
fairyfly_grasshopper/user_objects/FF Boundary.ghuser
fairyfly_grasshopper/user_objects/FF Cavity Material.ghuser
fairyfly_grasshopper/user_objects/FF Color Boundary Attributes.ghuser
fairyfly_grasshopper/user_objects/FF Color Shape Attributes.ghuser
fairyfly_grasshopper/user_objects/FF Deconstruct Material.ghuser
fairyfly_grasshopper/user_objects/FF Dump Objects.ghuser
fairyfly_grasshopper/user_objects/FF Load Objects.ghuser
fairyfly_grasshopper/user_objects/FF Meshing Control.ghuser
fairyfly_grasshopper/user_objects/FF Model to THMZ.ghuser
fairyfly_grasshopper/user_objects/FF Model.ghuser
fairyfly_grasshopper/user_objects/FF Radiant Environment.ghuser
fairyfly_grasshopper/user_objects/FF Read THERM Result.ghuser
fairyfly_grasshopper/user_objects/FF Read UFactor Result.ghuser
fairyfly_grasshopper/user_objects/FF Search Materials.ghuser
fairyfly_grasshopper/user_objects/FF Shape Attributes.ghuser
fairyfly_grasshopper/user_objects/FF Shape.ghuser
fairyfly_grasshopper/user_objects/FF Solid Material.ghuser
fairyfly_grasshopper-0.4.0.dist-info/licenses/LICENSE
fairyfly_grasshopper-0.4.0.dist-info/METADATA
fairyfly_grasshopper-0.4.0.dist-info/WHEEL
fairyfly_grasshopper-0.4.0.dist-info/top_level.txt
fairyfly_grasshopper-0.4.0.dist-info/RECORD
